{"$schema":"https://json-schema.org/draft/2020-12/schema","type":"object","required":["candidate_id","case_id","bank","raw_output","discrete_output","positive_scope","anti_scope","active","query_influence","authority","terminal_influence"],"properties":{"candidate_id":{"type":"string"},"case_id":{"type":"string"},"bank":{"type":"string"},"raw_output":{"type":"number"},"discrete_output":{"type":"integer"},"positive_scope":{"type":"boolean"},"anti_scope":{"type":"boolean"},"active":{"type":"boolean"},"query_influence":{"type":"number"},"authority":{"type":"string"},"terminal_influence":{"type":"number"}},"additionalProperties":false}

