{
  "all_passed": true,
  "authority": "L2",
  "case_id": "P7-GENUINELY-NEW-SEMANTIC-NEED-006",
  "certificate_hash": "3914266f9c53b2047375aa726b84a4871d3a0b45307e5f335021d24d04ac61d4",
  "certificate_id": "LC-2fadf5471f5e30184d2b",
  "obligations": {
    "authority": true,
    "counterfactual_stability": true,
    "evidence_integrity": true,
    "executable_scope": true,
    "hypothesis_separation": true,
    "interaction_safety": true,
    "kernel_preservation": true,
    "replay": true,
    "risk_justification": true,
    "witness_sufficiency": true
  },
  "parent_hash": "30fc68482707ef281befcf6cd42a4654d58e18a6999cdeb3d4ab682cd3640543",
  "surviving_hypotheses": [
    "P7-GENUINELY-NEW-SEMANTIC-NEED-006-SAFE"
  ],
  "terminal_action": "ACCEPT",
  "witness_ids": [
    "terminal_witness"
  ]
}
