{
  "case_id": "P7-ONE-QUERY-SEPARABLE-002",
  "hypotheses": [
    {
      "anti_scope": [
        "registered_neighbor_confounder"
      ],
      "authority": "L1",
      "decision_class": "safe",
      "discriminating_actions": [
        "P7-ONE-QUERY-SEPARABLE-002-TARGET",
        "P7-ONE-QUERY-SEPARABLE-002-DISTRACTOR"
      ],
      "hypothesis_id": "P7-ONE-QUERY-SEPARABLE-002-SAFE",
      "positive_scope": [
        "registered_case_family"
      ],
      "predicted_counterfactuals": [
        "nuisance_preserving_invariance",
        "causal_intervention_sensitivity"
      ],
      "predicted_witnesses": [
        "terminal_witness"
      ],
      "requirements": [
        {
          "field": "terminal_witness",
          "operator": "eq",
          "value": "safe"
        }
      ],
      "semantic_claim": "Visible evidence is compatible with a safe governed mechanism.",
      "terminal_consequence": "ACCEPT"
    },
    {
      "anti_scope": [
        "registered_neighbor_confounder"
      ],
      "authority": "L1",
      "decision_class": "unsafe",
      "discriminating_actions": [
        "P7-ONE-QUERY-SEPARABLE-002-TARGET",
        "P7-ONE-QUERY-SEPARABLE-002-DISTRACTOR"
      ],
      "hypothesis_id": "P7-ONE-QUERY-SEPARABLE-002-UNSAFE",
      "positive_scope": [
        "registered_case_family"
      ],
      "predicted_counterfactuals": [
        "nuisance_preserving_invariance",
        "causal_intervention_sensitivity"
      ],
      "predicted_witnesses": [
        "terminal_witness"
      ],
      "requirements": [
        {
          "field": "terminal_witness",
          "operator": "eq",
          "value": "unsafe"
        }
      ],
      "semantic_claim": "Visible evidence is compatible with an unsafe governed mechanism.",
      "terminal_consequence": "REJECT"
    }
  ],
  "initial_ambiguity_state": {
    "ambiguity_type": "missing_evidence",
    "case_id": "P7-ONE-QUERY-SEPARABLE-002",
    "evidence_hash": "0f1824ecf29ba06daab7324f5b1cfa5259e5872892bc7d5810bc8c23bc64dc68",
    "parent_hash": "70ac8195dbcd21bb6ae596af9532615cce6dc1092694ef8e015cac8f72dc1050",
    "round_index": 0,
    "safe_count": 1,
    "state_hash": "3ceab15ed4d8ee00ae3bf6426cab2904a14b1edd6e2e243b9779cdd4e03aa638",
    "surviving_hypotheses": [
      "P7-ONE-QUERY-SEPARABLE-002-SAFE",
      "P7-ONE-QUERY-SEPARABLE-002-UNSAFE"
    ],
    "unsafe_count": 1
  }
}
